dsdata/__init__.py
dsdata/config.py
dsdata/datasense-jdbc-client.jar
dsdata/dsdata.py
dsdata/util.py
dsdata/client/__init__.py
dsdata/client/api.py
dsdata/client/_swagger/__init__.py
dsdata/client/_swagger/api_client.py
dsdata/client/_swagger/configuration.py
dsdata/client/_swagger/rest.py
dsdata/client/_swagger/apis/__init__.py
dsdata/client/_swagger/apis/datasets_api.py
dsdata/client/_swagger/apis/upload_object_tags_api.py
dsdata/db/__init__.py
dsdata/hosts/__init__.py
dsdata/models/__init__.py
dsdata/models/dataset.py
dsdata-1.1.0.3.dist-info/METADATA
dsdata-1.1.0.3.dist-info/WHEEL
dsdata-1.1.0.3.dist-info/top_level.txt
dsdata-1.1.0.3.dist-info/RECORD
