Metadata-Version: 2.1
Name: dsdata
Version: 1.1.0.3
Summary: load and upload datasense platform of data
Author: datasense developer
Requires-Python: >=3.7
Requires-Dist: pandas
Requires-Dist: JayDeBeApi
Requires-Dist: requests
Requires-Dist: tqdm
